{
  "_class": "artboard",
  "backgroundColor": {
    "_class": "color",
    "alpha": 1,
    "blue": 1,
    "do_objectID": "547D5E50-1961-480C-88D2-2AC8CCA0F2EB",
    "green": 1,
    "red": 1
  },
  "booleanOperation": -1,
  "clippingMaskMode": 0,
  "do_objectID": "82CAC030-543F-42DD-8B4E-EF5EBFA5A4BF",
  "exportOptions": {
    "_class": "exportOptions",
    "do_objectID": "F58D7CD7-FD42-4801-83E4-98877C55AE37",
    "exportFormats": [
      {
        "_class": "exportFormat",
        "absoluteSize": 0,
        "fileFormat": "png",
        "name": "",
        "namingScheme": 0,
        "scale": 3,
        "visibleScaleType": 0
      }
    ],
    "includedLayerIds": [
    ],
    "layerOptions": 0,
    "shouldTrim": false
  },
  "frame": {
    "_class": "rect",
    "constrainProportions": false,
    "do_objectID": "303FA854-5C9A-4F76-8A36-11416E63ECB9",
    "height": 740,
    "width": 360,
    "x": 12062,
    "y": 728
  },
  "groupLayout": {
    "_class": "MSImmutableFreeformGroupLayout",
    "do_objectID": "A4CC4997-1615-4644-AC4A-1CC03E8C71C9"
  },
  "hasBackgroundColor": false,
  "hasClickThrough": false,
  "hasClippingMask": false,
  "horizontalRulerData": {
    "_class": "rulerData",
    "base": 0,
    "do_objectID": "9D5198DB-3AFC-43D3-907D-A68C236F52B2",
    "guides": [
    ]
  },
  "includeBackgroundColorInExport": true,
  "includeInCloudUpload": true,
  "isFixedToViewport": false,
  "isFlippedHorizontal": false,
  "isFlippedVertical": false,
  "isFlowHome": false,
  "isLocked": false,
  "isVisible": true,
  "layerListExpandedType": 2,
  "layers": [
    {
      "class": "group",
      "id": "32694CB0-A0F5-4B95-A4C8-7C4ED1558A82"
    }
  ],
  "name": "garuda-landing",
  "nameIsFixed": true,
  "presetDictionary": {
    "allowResizedMatching": 0,
    "height": 740,
    "name": "Galaxy S8",
    "offersLandscapeVariant": 1,
    "width": 360
  },
  "resizesContent": false,
  "resizingConstraint": 63,
  "resizingType": 0,
  "rotation": 0,
  "shouldBreakMaskChain": true,
  "style": {
    "_class": "style",
    "do_objectID": "057687C4-5A61-42F4-ACDD-6EB95B1AACB2",
    "endMarkerType": 0,
    "miterLimit": 10,
    "startMarkerType": 0,
    "windingRule": 1
  },
  "userInfo": {
    "io.magicsketch.mirror": {
      "highestQuality": 1
    }
  },
  "verticalRulerData": {
    "_class": "rulerData",
    "base": 0,
    "do_objectID": "BFB97F8E-8A3A-4157-93D6-1F29D435F09B",
    "guides": [
    ]
  }
}