{
  "_class": "group",
  "booleanOperation": -1,
  "clippingMaskMode": 0,
  "do_objectID": "BBFD6E3E-7FBC-4C16-AB46-9C571FEC919E",
  "exportOptions": {
    "_class": "exportOptions",
    "do_objectID": "BEB7FD48-4667-4B80-80C0-F4AE7228BC51",
    "exportFormats": [
    ],
    "includedLayerIds": [
    ],
    "layerOptions": 0,
    "shouldTrim": false
  },
  "frame": {
    "_class": "rect",
    "constrainProportions": false,
    "do_objectID": "830258C1-A871-4BF6-A3F0-3544E8470BF7",
    "height": 346,
    "width": 471,
    "x": 20,
    "y": 26
  },
  "groupLayout": {
    "_class": "MSImmutableFreeformGroupLayout",
    "do_objectID": "A93C123F-818F-404C-8758-5C620F2C7BDF"
  },
  "hasClickThrough": false,
  "hasClippingMask": false,
  "isFixedToViewport": false,
  "isFlippedHorizontal": false,
  "isFlippedVertical": false,
  "isLocked": false,
  "isVisible": true,
  "layerListExpandedType": 2,
  "layers": [
    {
      "class": "group",
      "id": "1C2B05ED-8E19-4EDD-8408-93DA485A7062"
    },
    {
      "class": "group",
      "id": "51CF96EB-A560-4057-9202-7A6B1F325FF6"
    },
    {
      "class": "group",
      "id": "E9038591-5189-4D28-AB09-40902E0FDFC7"
    },
    {
      "class": "group",
      "id": "E419634F-EB59-4D57-BF82-509521E1FF21"
    },
    {
      "class": "text",
      "id": "C39AE9B1-67B3-4FFC-8EA4-3841DCF9FDA4"
    }
  ],
  "name": "Group 16",
  "nameIsFixed": false,
  "resizingConstraint": 63,
  "resizingType": 0,
  "rotation": 0,
  "shouldBreakMaskChain": false,
  "style": {
    "_class": "style",
    "do_objectID": "6880014A-CCD0-47BF-B130-1855AC086F5F",
    "endMarkerType": 0,
    "miterLimit": 10,
    "startMarkerType": 0,
    "windingRule": 1
  }
}