{
  "_class": "group",
  "booleanOperation": -1,
  "clippingMaskMode": 0,
  "do_objectID": "8922E2FA-0278-4C7F-A171-82C11D574DC3",
  "exportOptions": {
    "_class": "exportOptions",
    "do_objectID": "A7233DAF-1298-4AE8-A23B-CAF60261765F",
    "exportFormats": [
    ],
    "includedLayerIds": [
    ],
    "layerOptions": 0,
    "shouldTrim": false
  },
  "frame": {
    "_class": "rect",
    "constrainProportions": false,
    "do_objectID": "97378925-E914-4897-BB4E-8330B03961E1",
    "height": 46,
    "width": 343,
    "x": 0,
    "y": 0
  },
  "groupLayout": {
    "_class": "MSImmutableFreeformGroupLayout",
    "do_objectID": "4AD28212-1017-4A08-B478-687E80CF4726"
  },
  "hasClickThrough": false,
  "hasClippingMask": false,
  "isFixedToViewport": false,
  "isFlippedHorizontal": false,
  "isFlippedVertical": false,
  "isLocked": false,
  "isVisible": true,
  "layerListExpandedType": 0,
  "layers": [
    {
      "class": "rectangle",
      "id": "460D15A9-DBF0-4896-8478-FC91B96DC4E5"
    },
    {
      "class": "text",
      "id": "88B0C9D8-1550-4F1A-9F66-B4C1394446AD"
    }
  ],
  "name": "Group",
  "nameIsFixed": false,
  "resizingConstraint": 63,
  "resizingType": 0,
  "rotation": 0,
  "shouldBreakMaskChain": false,
  "style": {
    "_class": "style",
    "do_objectID": "8648CB16-A006-467B-9FFA-698E9083FF99",
    "endMarkerType": 0,
    "miterLimit": 10,
    "startMarkerType": 0,
    "windingRule": 1
  }
}