{
  "_class": "group",
  "booleanOperation": -1,
  "clippingMaskMode": 0,
  "do_objectID": "242271C8-F34D-4F7B-A75F-D350DFF2A638",
  "exportOptions": {
    "_class": "exportOptions",
    "do_objectID": "ED9DF89F-F338-42ED-B7FD-706ACE3C1AE9",
    "exportFormats": [
    ],
    "includedLayerIds": [
    ],
    "layerOptions": 0,
    "shouldTrim": false
  },
  "frame": {
    "_class": "rect",
    "constrainProportions": false,
    "do_objectID": "8413900C-1B66-4EEC-8A32-57BA7057D3FB",
    "height": 21,
    "width": 237,
    "x": 0,
    "y": 0
  },
  "groupLayout": {
    "_class": "MSImmutableFreeformGroupLayout",
    "do_objectID": "8C359C85-5EBB-4BDA-9129-1D0A4B75FE4B"
  },
  "hasClickThrough": false,
  "hasClippingMask": false,
  "isFixedToViewport": false,
  "isFlippedHorizontal": false,
  "isFlippedVertical": false,
  "isLocked": false,
  "isVisible": true,
  "layerListExpandedType": 2,
  "layers": [
    {
      "class": "text",
      "id": "5FA4B860-DD2F-4824-B931-6178A62E1A99"
    },
    {
      "class": "shapePath",
      "id": "F7CEE48C-3B78-4635-8DCC-5CE32F94BE0C"
    }
  ],
  "name": "Center",
  "nameIsFixed": false,
  "resizingConstraint": 63,
  "resizingType": 0,
  "rotation": 0,
  "shouldBreakMaskChain": false,
  "style": {
    "_class": "style",
    "do_objectID": "907D1D27-AB6A-4881-8A86-F57C031EC0D7",
    "endMarkerType": 0,
    "miterLimit": 10,
    "startMarkerType": 0,
    "windingRule": 1
  }
}