{
  "_class": "group",
  "booleanOperation": -1,
  "clippingMaskMode": 0,
  "do_objectID": "C9475E5D-8E69-4D99-8A88-EBBB12FF2B80",
  "exportOptions": {
    "_class": "exportOptions",
    "do_objectID": "521DC929-6298-4C5C-B5E2-16FE6CC57BF2",
    "exportFormats": [
    ],
    "includedLayerIds": [
    ],
    "layerOptions": 0,
    "shouldTrim": false
  },
  "frame": {
    "_class": "rect",
    "constrainProportions": false,
    "do_objectID": "2B02C487-B310-4956-8BB1-40656833B15E",
    "height": 57,
    "width": 94,
    "x": 94,
    "y": 0
  },
  "groupLayout": {
    "_class": "MSImmutableFreeformGroupLayout",
    "do_objectID": "26B4F378-94DD-4F92-8C5C-FA4C518C114A"
  },
  "hasClickThrough": false,
  "hasClippingMask": false,
  "isFixedToViewport": false,
  "isFlippedHorizontal": false,
  "isFlippedVertical": false,
  "isLocked": false,
  "isVisible": true,
  "layerListExpandedType": 0,
  "layers": [
    {
      "class": "rectangle",
      "id": "A02B28D5-9E93-489E-9327-D43B19F95406"
    },
    {
      "class": "text",
      "id": "79A9F61C-B859-456A-8C11-942AC9317013"
    },
    {
      "class": "group",
      "id": "26B6219E-4BE2-4B3A-B7A4-77EA5866369E"
    }
  ],
  "name": "PROFILE_ICN Copy 3",
  "nameIsFixed": true,
  "resizingConstraint": 63,
  "resizingType": 0,
  "rotation": 0,
  "shouldBreakMaskChain": false,
  "style": {
    "_class": "style",
    "do_objectID": "DFD01899-6020-497B-9996-2EFC5EE4CFDF",
    "endMarkerType": 0,
    "miterLimit": 10,
    "startMarkerType": 0,
    "windingRule": 1
  }
}