{
  "_class": "group",
  "booleanOperation": -1,
  "clippingMaskMode": 0,
  "do_objectID": "FBB32E7E-26FA-4BA9-80F8-0EEF7DCDA86A",
  "exportOptions": {
    "_class": "exportOptions",
    "do_objectID": "99E20547-7B7B-49BB-A1B7-75F05DD615E5",
    "exportFormats": [
    ],
    "includedLayerIds": [
    ],
    "layerOptions": 0,
    "shouldTrim": false
  },
  "frame": {
    "_class": "rect",
    "constrainProportions": false,
    "do_objectID": "F354B0C1-0D03-4745-996A-1F08184855B8",
    "height": 20,
    "width": 56,
    "x": 0,
    "y": 0
  },
  "groupLayout": {
    "_class": "MSImmutableFreeformGroupLayout",
    "do_objectID": "EA3FA7D7-A0CA-4357-9842-81CFA8E8CFFF"
  },
  "hasClickThrough": false,
  "hasClippingMask": false,
  "isFixedToViewport": false,
  "isFlippedHorizontal": false,
  "isFlippedVertical": false,
  "isLocked": false,
  "isVisible": true,
  "layerListExpandedType": 0,
  "layers": [
    {
      "class": "group",
      "id": "8332AEE9-94F0-427C-BA67-301F4BBF1B60"
    },
    {
      "class": "text",
      "id": "CF989540-753F-4AB4-8575-EBAB63134272"
    }
  ],
  "name": "Group 36",
  "nameIsFixed": false,
  "resizingConstraint": 63,
  "resizingType": 0,
  "rotation": 0,
  "shouldBreakMaskChain": false,
  "style": {
    "_class": "style",
    "do_objectID": "B8084E38-3E47-4558-98E2-58D3A411F188",
    "endMarkerType": 0,
    "miterLimit": 10,
    "startMarkerType": 0,
    "windingRule": 1
  }
}