{
  "_class": "group",
  "booleanOperation": -1,
  "clippingMaskMode": 0,
  "do_objectID": "A85FA0C1-79FC-4B59-B32B-5654CFA25569",
  "exportOptions": {
    "_class": "exportOptions",
    "do_objectID": "F71B8446-B404-479E-AED5-5899394751E3",
    "exportFormats": [
    ],
    "includedLayerIds": [
    ],
    "layerOptions": 0,
    "shouldTrim": false
  },
  "frame": {
    "_class": "rect",
    "constrainProportions": false,
    "do_objectID": "775D3C9E-1474-44AD-A1E4-59895DE555F9",
    "height": 48,
    "width": 495,
    "x": 0,
    "y": 612
  },
  "groupLayout": {
    "_class": "MSImmutableFreeformGroupLayout",
    "do_objectID": "724194B7-B3E1-4D1E-B815-4883ECE9EE4E"
  },
  "hasClickThrough": false,
  "hasClippingMask": false,
  "isFixedToViewport": false,
  "isFlippedHorizontal": false,
  "isFlippedVertical": false,
  "isLocked": false,
  "isVisible": true,
  "layerListExpandedType": 0,
  "layers": [
    {
      "class": "rectangle",
      "id": "4A0171EB-FF52-4B34-81D8-8E2C04385DEC"
    },
    {
      "class": "text",
      "id": "5DD3EBD6-6D9C-4005-AB60-51DC34AE72AC"
    }
  ],
  "name": "Group 6 Copy",
  "nameIsFixed": false,
  "resizingConstraint": 63,
  "resizingType": 0,
  "rotation": 0,
  "shouldBreakMaskChain": false,
  "style": {
    "_class": "style",
    "do_objectID": "00156A7E-BD0D-468D-AF97-3929A82654A2",
    "endMarkerType": 0,
    "miterLimit": 10,
    "startMarkerType": 0,
    "windingRule": 1
  }
}