{
  "_class": "group",
  "booleanOperation": -1,
  "clippingMaskMode": 0,
  "do_objectID": "63908186-145F-4037-8F57-082F3FB1DE4E",
  "exportOptions": {
    "_class": "exportOptions",
    "do_objectID": "1BD7E301-2067-4CFB-B9D6-B3400947B986",
    "exportFormats": [
    ],
    "includedLayerIds": [
    ],
    "layerOptions": 0,
    "shouldTrim": false
  },
  "frame": {
    "_class": "rect",
    "constrainProportions": false,
    "do_objectID": "1C240162-B263-469E-BFAC-3114BAFC8E8A",
    "height": 14,
    "width": 104,
    "x": 162,
    "y": 0
  },
  "groupLayout": {
    "_class": "MSImmutableFreeformGroupLayout",
    "do_objectID": "B8966AB6-4A28-4AE3-B506-5BC9C0A0F92F"
  },
  "hasClickThrough": false,
  "hasClippingMask": false,
  "isFixedToViewport": false,
  "isFlippedHorizontal": false,
  "isFlippedVertical": false,
  "isLocked": false,
  "isVisible": true,
  "layerListExpandedType": 2,
  "layers": [
    {
      "class": "text",
      "id": "D9CA1482-9800-41E1-A12B-D2CAC16321A6"
    },
    {
      "class": "group",
      "id": "F6105BA7-60AD-429E-954C-91F941E89BE0"
    }
  ],
  "name": "Group 3",
  "nameIsFixed": false,
  "resizingConstraint": 63,
  "resizingType": 0,
  "rotation": 0,
  "shouldBreakMaskChain": false,
  "style": {
    "_class": "style",
    "do_objectID": "F653944D-9017-4E01-804A-37D276A98023",
    "endMarkerType": 0,
    "miterLimit": 10,
    "startMarkerType": 0,
    "windingRule": 1
  }
}