{
  "_class": "group",
  "booleanOperation": -1,
  "clippingMaskMode": 0,
  "do_objectID": "6E8EA5C7-1B51-4AEA-AF0B-CA0EA6C23939",
  "exportOptions": {
    "_class": "exportOptions",
    "do_objectID": "4FC6234E-6DBA-4F58-8DDF-8D18C7E46B60",
    "exportFormats": [
    ],
    "includedLayerIds": [
    ],
    "layerOptions": 0,
    "shouldTrim": false
  },
  "frame": {
    "_class": "rect",
    "constrainProportions": false,
    "do_objectID": "B4DA4782-8FEF-43FF-A000-0E21DE0E05E4",
    "height": 16,
    "width": 16,
    "x": 39,
    "y": 16
  },
  "groupLayout": {
    "_class": "MSImmutableFreeformGroupLayout",
    "do_objectID": "C0512640-027A-4BFD-B647-C62EA759EAF5"
  },
  "hasClickThrough": false,
  "hasClippingMask": false,
  "isFixedToViewport": false,
  "isFlippedHorizontal": false,
  "isFlippedVertical": false,
  "isLocked": false,
  "isVisible": true,
  "layerListExpandedType": 0,
  "layers": [
    {
      "class": "shapeGroup",
      "id": "534A434B-178F-4CD1-AA18-B9846B8EFBA4"
    },
    {
      "class": "shapeGroup",
      "id": "BB28477B-3B57-464E-B676-9B5F85888746"
    }
  ],
  "name": "Group 2",
  "nameIsFixed": false,
  "resizingConstraint": 63,
  "resizingType": 0,
  "rotation": 0,
  "shouldBreakMaskChain": false,
  "style": {
    "_class": "style",
    "blur": {
      "_class": "blur",
      "center": "{0.5, 0.5}",
      "do_objectID": "E1CE2E50-0765-4644-B799-C659FE8E42FC",
      "isEnabled": false,
      "motionAngle": 0,
      "radius": 3.636363636363637,
      "saturation": 1,
      "type": 0
    },
    "do_objectID": "B9C7D8FF-6068-46A4-BAFC-24B834274EF3",
    "endMarkerType": 0,
    "miterLimit": 10,
    "startMarkerType": 0,
    "windingRule": 1
  }
}