{
  "_class": "group",
  "booleanOperation": -1,
  "clippingMaskMode": 0,
  "do_objectID": "14F87F7F-3492-43B4-9144-1B6646C4F6BF",
  "exportOptions": {
    "_class": "exportOptions",
    "do_objectID": "7F6D5EE9-4344-4494-A3D8-9D0B5E2A65C0",
    "exportFormats": [
    ],
    "includedLayerIds": [
    ],
    "layerOptions": 0,
    "shouldTrim": false
  },
  "frame": {
    "_class": "rect",
    "constrainProportions": false,
    "do_objectID": "926F91AC-9A00-48CD-A003-8187CCF06C3A",
    "height": 16,
    "width": 15,
    "x": 40,
    "y": 16
  },
  "groupLayout": {
    "_class": "MSImmutableFreeformGroupLayout",
    "do_objectID": "943C11F7-D01E-4725-969F-86A459024223"
  },
  "hasClickThrough": false,
  "hasClippingMask": false,
  "isFixedToViewport": false,
  "isFlippedHorizontal": false,
  "isFlippedVertical": false,
  "isLocked": false,
  "isVisible": true,
  "layerListExpandedType": 2,
  "layers": [
    {
      "class": "shapeGroup",
      "id": "43289C2A-8A2D-4B8C-B39E-8F6AE3FC3E98"
    }
  ],
  "name": "package",
  "nameIsFixed": false,
  "resizingConstraint": 63,
  "resizingType": 0,
  "rotation": 0,
  "shouldBreakMaskChain": false,
  "style": {
    "_class": "style",
    "blur": {
      "_class": "blur",
      "center": "{0.5, 0.5}",
      "do_objectID": "5A3F1D83-1DBE-4139-A977-7E6664E64E41",
      "isEnabled": false,
      "motionAngle": 0,
      "radius": 0.3933614627285514,
      "saturation": 1,
      "type": 0
    },
    "do_objectID": "F371942F-ACAC-4162-8BF7-AAE932DDB7F1",
    "endMarkerType": 0,
    "miterLimit": 10,
    "startMarkerType": 0,
    "windingRule": 1
  }
}