{
  "_class": "group",
  "booleanOperation": -1,
  "clippingMaskMode": 0,
  "do_objectID": "23BADE66-469A-4922-9C77-01798B353BE4",
  "exportOptions": {
    "_class": "exportOptions",
    "do_objectID": "3DA51EEB-9C56-4D63-A2C7-C1BC8C329CFA",
    "exportFormats": [
    ],
    "includedLayerIds": [
    ],
    "layerOptions": 0,
    "shouldTrim": false
  },
  "frame": {
    "_class": "rect",
    "constrainProportions": false,
    "do_objectID": "62D823D4-F978-4152-B237-0D8887A5BC9B",
    "height": 57,
    "width": 94,
    "x": 0,
    "y": 0
  },
  "groupLayout": {
    "_class": "MSImmutableFreeformGroupLayout",
    "do_objectID": "84AB80C3-B519-44F2-B826-D2490F520AAB"
  },
  "hasClickThrough": false,
  "hasClippingMask": false,
  "isFixedToViewport": false,
  "isFlippedHorizontal": false,
  "isFlippedVertical": false,
  "isLocked": false,
  "isVisible": true,
  "layerListExpandedType": 0,
  "layers": [
    {
      "class": "rectangle",
      "id": "E5A91AE9-F2E2-43E5-9F22-36F2EE04DD44"
    },
    {
      "class": "text",
      "id": "E2822F02-0428-4B29-B361-7581BE021D26"
    },
    {
      "class": "shapeGroup",
      "id": "4624CB9C-B1D4-461C-9B5C-3964180D1243"
    }
  ],
  "name": "PROFILE_ICN Copy",
  "nameIsFixed": true,
  "resizingConstraint": 63,
  "resizingType": 0,
  "rotation": 0,
  "shouldBreakMaskChain": false,
  "style": {
    "_class": "style",
    "do_objectID": "560EE3EF-0BE4-4454-BFB4-536989859A86",
    "endMarkerType": 0,
    "miterLimit": 10,
    "startMarkerType": 0,
    "windingRule": 1
  }
}