{
  "_class": "group",
  "booleanOperation": -1,
  "clippingMaskMode": 0,
  "do_objectID": "8E7A2F1E-9ECB-4C6D-BB8A-C8EEEF193716",
  "exportOptions": {
    "_class": "exportOptions",
    "do_objectID": "25291F1E-2528-4EC4-9913-56F12D3ED865",
    "exportFormats": [
    ],
    "includedLayerIds": [
    ],
    "layerOptions": 0,
    "shouldTrim": false
  },
  "frame": {
    "_class": "rect",
    "constrainProportions": false,
    "do_objectID": "B6FAD0CB-55C6-434A-A8DC-63693922EA5C",
    "height": 21,
    "width": 343,
    "x": 16,
    "y": 55
  },
  "groupLayout": {
    "_class": "MSImmutableFreeformGroupLayout",
    "do_objectID": "C6CBC7DD-A121-4A7C-931F-9A4C9681B759"
  },
  "hasClickThrough": false,
  "hasClippingMask": false,
  "isFixedToViewport": false,
  "isFlippedHorizontal": false,
  "isFlippedVertical": false,
  "isLocked": false,
  "isVisible": true,
  "layerListExpandedType": 2,
  "layers": [
    {
      "class": "shapePath",
      "id": "0A832086-53B4-4727-851F-3A21826ADE5A"
    },
    {
      "class": "group",
      "id": "B3E05A21-49D1-497F-8F87-451C5631D7DD"
    },
    {
      "class": "group",
      "id": "767A9DD3-B39C-4177-A7C8-7CB528C5F0BF"
    }
  ],
  "name": "Group",
  "nameIsFixed": false,
  "resizingConstraint": 63,
  "resizingType": 0,
  "rotation": 0,
  "shouldBreakMaskChain": false,
  "style": {
    "_class": "style",
    "do_objectID": "5D292DCF-E7C2-4A3B-B43F-AD0844E1F06D",
    "endMarkerType": 0,
    "miterLimit": 10,
    "startMarkerType": 0,
    "windingRule": 1
  }
}