{
  "_class": "shapeGroup",
  "booleanOperation": 0,
  "clippingMaskMode": 0,
  "do_objectID": "84D5DFA5-A6EE-42EA-854E-B7FC9F6724B4",
  "exportOptions": {
    "_class": "exportOptions",
    "do_objectID": "D951B067-1ACE-41D2-BEC3-90D6AB9742DD",
    "exportFormats": [
      {
        "_class": "exportFormat",
        "absoluteSize": 0,
        "fileFormat": "svg",
        "name": "",
        "namingScheme": 0,
        "scale": 1,
        "visibleScaleType": 0
      }
    ],
    "includedLayerIds": [
    ],
    "layerOptions": 0,
    "shouldTrim": false
  },
  "frame": {
    "_class": "rect",
    "constrainProportions": false,
    "do_objectID": "EA8E1608-52FB-481A-A15D-B21D9D0D0795",
    "height": 15.64444444444445,
    "width": 15.64444444444445,
    "x": 311.9999999999999,
    "y": 392.9999999999998
  },
  "groupLayout": {
    "_class": "MSImmutableFreeformGroupLayout",
    "do_objectID": "15C2187A-D048-4065-BFD9-6AE3C3BFC217"
  },
  "hasClickThrough": false,
  "hasClippingMask": false,
  "isFixedToViewport": false,
  "isFlippedHorizontal": false,
  "isFlippedVertical": false,
  "isLocked": false,
  "isVisible": true,
  "layerListExpandedType": 1,
  "layers": [
    {
      "class": "shapePath",
      "id": "113B9576-681F-4B25-9A99-3B05867BB009"
    },
    {
      "class": "shapePath",
      "id": "FAED368B-EF0A-4FEB-A95E-7F77A1259EA2"
    }
  ],
  "name": "Shape",
  "nameIsFixed": false,
  "resizingConstraint": 63,
  "resizingType": 0,
  "rotation": 0,
  "shouldBreakMaskChain": false,
  "style": {
    "_class": "style",
    "blur": {
      "_class": "blur",
      "center": "{0.5, 0.5}",
      "do_objectID": "0F29A2BC-6A84-4F09-9F4E-958942DE05BB",
      "isEnabled": false,
      "motionAngle": 0,
      "radius": 3.555555555555556,
      "saturation": 1,
      "type": 0
    },
    "do_objectID": "FE8419CD-8B14-4303-AA4A-0B4F4AA4B9BA",
    "endMarkerType": 0,
    "fills": [
      {
        "_class": "fill",
        "color": {
          "_class": "color",
          "alpha": 1,
          "blue": 0.3137254901960784,
          "green": 0.2941176470588235,
          "red": 0.2627450980392157
        },
        "fillType": 0,
        "isEnabled": true,
        "noiseIndex": 0,
        "noiseIntensity": 0,
        "patternFillType": 1,
        "patternTileScale": 1
      }
    ],
    "miterLimit": 10,
    "startMarkerType": 0,
    "windingRule": 1
  },
  "windingRule": 1
}