{
  "_class": "group",
  "booleanOperation": -1,
  "clippingMaskMode": 0,
  "do_objectID": "B215EF14-80BB-43F9-8433-687575758438",
  "exportOptions": {
    "_class": "exportOptions",
    "do_objectID": "965EF734-5956-4B93-BD0D-9EF1AD5E1CED",
    "exportFormats": [
    ],
    "includedLayerIds": [
    ],
    "layerOptions": 0,
    "shouldTrim": false
  },
  "frame": {
    "_class": "rect",
    "constrainProportions": false,
    "do_objectID": "E7AB31A0-0483-4447-8D09-0B57480354DA",
    "height": 405,
    "width": 478,
    "x": 136,
    "y": 741
  },
  "groupLayout": {
    "_class": "MSImmutableFreeformGroupLayout",
    "do_objectID": "14C376C6-5979-4A57-B44C-DEA7B766AA52"
  },
  "hasClickThrough": false,
  "hasClippingMask": false,
  "isFixedToViewport": false,
  "isFlippedHorizontal": false,
  "isFlippedVertical": false,
  "isLocked": false,
  "isVisible": true,
  "layerListExpandedType": 0,
  "layers": [
    {
      "class": "oval",
      "id": "B4ECB9A0-4336-4AE2-96ED-8EAC674DC836"
    },
    {
      "class": "oval",
      "id": "DE9FCB1B-E81F-4315-842F-5115E7B6150E"
    }
  ],
  "name": "Bottom_Blob",
  "nameIsFixed": true,
  "resizingConstraint": 63,
  "resizingType": 0,
  "rotation": 0,
  "shouldBreakMaskChain": false,
  "style": {
    "_class": "style",
    "contextSettings": {
      "_class": "graphicsContextSettings",
      "blendMode": 0,
      "do_objectID": "C404981E-8D89-4C6C-A25C-B374599FAC39",
      "opacity": 0.2000000029802322
    },
    "do_objectID": "4CD17808-9C83-4DEA-BD6E-8C79DA7DDA37",
    "endMarkerType": 0,
    "miterLimit": 10,
    "startMarkerType": 0,
    "windingRule": 1
  }
}