{
  "_class": "group",
  "booleanOperation": -1,
  "clippingMaskMode": 0,
  "do_objectID": "464D3915-3CF8-466A-864C-8AC8B3516B1C",
  "exportOptions": {
    "_class": "exportOptions",
    "do_objectID": "2233EDE4-C722-458C-930D-B15AB3A43F50",
    "exportFormats": [
    ],
    "includedLayerIds": [
    ],
    "layerOptions": 0,
    "shouldTrim": false
  },
  "frame": {
    "_class": "rect",
    "constrainProportions": false,
    "do_objectID": "C29E5DA9-3207-4B1B-AEF1-04CBABB44203",
    "height": 126,
    "width": 343,
    "x": 16,
    "y": 269
  },
  "groupLayout": {
    "_class": "MSImmutableFreeformGroupLayout",
    "do_objectID": "931372D3-A25F-4039-BAD9-D8DEEEDEABFF"
  },
  "hasClickThrough": false,
  "hasClippingMask": false,
  "isFixedToViewport": false,
  "isFlippedHorizontal": false,
  "isFlippedVertical": false,
  "isLocked": false,
  "isVisible": true,
  "layerListExpandedType": 2,
  "layers": [
    {
      "class": "rectangle",
      "id": "EF7347A3-2DD8-42CD-B22B-8E752431BC52"
    },
    {
      "class": "group",
      "id": "A55B10E6-884D-479F-8E30-7FE2560AEB71"
    },
    {
      "class": "group",
      "id": "3C742490-13EF-491C-A3FD-CCDA2CFD42DD"
    }
  ],
  "name": "Group 2",
  "nameIsFixed": false,
  "resizingConstraint": 63,
  "resizingType": 0,
  "rotation": 0,
  "shouldBreakMaskChain": false,
  "style": {
    "_class": "style",
    "do_objectID": "F77BC91E-71FB-4C2A-BE7D-AE5989D409F0",
    "endMarkerType": 0,
    "miterLimit": 10,
    "startMarkerType": 0,
    "windingRule": 1
  }
}