{
  "_class": "group",
  "booleanOperation": -1,
  "clippingMaskMode": 0,
  "do_objectID": "A6D8A8FD-334A-4652-B7C2-A39F83D66C02",
  "exportOptions": {
    "_class": "exportOptions",
    "do_objectID": "F842320B-03DA-48CA-983B-35DDFC61DFD6",
    "exportFormats": [
    ],
    "includedLayerIds": [
    ],
    "layerOptions": 0,
    "shouldTrim": false
  },
  "frame": {
    "_class": "rect",
    "constrainProportions": false,
    "do_objectID": "7400DF65-00CF-4357-A257-41BE6F076240",
    "height": 16,
    "width": 15,
    "x": 40,
    "y": 17
  },
  "groupLayout": {
    "_class": "MSImmutableFreeformGroupLayout",
    "do_objectID": "B860DBA9-5C47-480D-98EE-25CC8E3B504A"
  },
  "hasClickThrough": false,
  "hasClippingMask": false,
  "isFixedToViewport": false,
  "isFlippedHorizontal": false,
  "isFlippedVertical": false,
  "isLocked": false,
  "isVisible": true,
  "layerListExpandedType": 0,
  "layers": [
    {
      "class": "shapeGroup",
      "id": "6D632C93-06CC-4E03-83C9-9F3C715D3971"
    },
    {
      "class": "shapePath",
      "id": "3A5BAA6E-8CBC-4822-9911-B46937BD228D"
    },
    {
      "class": "shapePath",
      "id": "E2D387B2-D46E-4136-AEFA-C3AE45CF7F70"
    },
    {
      "class": "shapeGroup",
      "id": "1E44A9B1-ADBE-4EFE-B27D-14F5BCF2EBB2"
    }
  ],
  "name": "Group 3",
  "nameIsFixed": false,
  "resizingConstraint": 63,
  "resizingType": 0,
  "rotation": 0,
  "shouldBreakMaskChain": false,
  "style": {
    "_class": "style",
    "blur": {
      "_class": "blur",
      "center": "{0.5, 0.5}",
      "do_objectID": "47E56B49-A868-4DD8-BE99-A8994BCDE80F",
      "isEnabled": false,
      "motionAngle": 0,
      "radius": 3.809523809523809,
      "saturation": 1,
      "type": 0
    },
    "do_objectID": "87CC0D46-BA27-44C0-8D8C-968ECBFB13AF",
    "endMarkerType": 0,
    "miterLimit": 10,
    "startMarkerType": 0,
    "windingRule": 1
  }
}