{
  "_class": "group",
  "booleanOperation": -1,
  "clippingMaskMode": 0,
  "do_objectID": "D715E8E6-670E-4DF2-AD69-33B4B0DFE17A",
  "exportOptions": {
    "_class": "exportOptions",
    "do_objectID": "D0A03BD5-7503-452C-A483-4EDD0839B8EF",
    "exportFormats": [
    ],
    "includedLayerIds": [
    ],
    "layerOptions": 0,
    "shouldTrim": false
  },
  "frame": {
    "_class": "rect",
    "constrainProportions": false,
    "do_objectID": "9771F48D-D175-4DEF-BB0C-B54DB8E4AAA3",
    "height": 19,
    "width": 343,
    "x": 0,
    "y": 17
  },
  "groupLayout": {
    "_class": "MSImmutableFreeformGroupLayout",
    "do_objectID": "41A1FF1D-62DA-458F-B298-DBC07003FE56"
  },
  "hasClickThrough": false,
  "hasClippingMask": false,
  "isFixedToViewport": false,
  "isFlippedHorizontal": false,
  "isFlippedVertical": false,
  "isLocked": false,
  "isVisible": true,
  "layerListExpandedType": 0,
  "layers": [
    {
      "class": "text",
      "id": "10D581DB-500B-402F-8543-DC206BD88BFD"
    },
    {
      "class": "text",
      "id": "C50829C9-2B55-4B1F-9335-CC19592074D4"
    }
  ],
  "name": "Group 9 Copy",
  "nameIsFixed": false,
  "resizingConstraint": 63,
  "resizingType": 0,
  "rotation": 0,
  "shouldBreakMaskChain": false,
  "style": {
    "_class": "style",
    "do_objectID": "C8EBAF83-B64D-4BA9-84AB-C509473F8A93",
    "endMarkerType": 0,
    "miterLimit": 10,
    "startMarkerType": 0,
    "windingRule": 1
  }
}