{
  "_class": "group",
  "booleanOperation": 0,
  "clippingMaskMode": 0,
  "do_objectID": "74A355ED-4F24-4633-9ACD-911C67014E9E",
  "exportOptions": {
    "_class": "exportOptions",
    "do_objectID": "33F090FD-AA5D-4E4E-8F17-A00FF69B5E29",
    "exportFormats": [
    ],
    "includedLayerIds": [
    ],
    "layerOptions": 0,
    "shouldTrim": false
  },
  "frame": {
    "_class": "rect",
    "constrainProportions": false,
    "do_objectID": "A12A8FB3-7BE7-450C-94F1-3CE523B2C029",
    "height": 24,
    "width": 24,
    "x": 29,
    "y": 16
  },
  "groupLayout": {
    "_class": "MSImmutableFreeformGroupLayout",
    "do_objectID": "1AF959F9-C557-4086-8931-EAE9F207F23F"
  },
  "hasClickThrough": false,
  "hasClippingMask": false,
  "isFixedToViewport": false,
  "isFlippedHorizontal": false,
  "isFlippedVertical": false,
  "isLocked": false,
  "isVisible": true,
  "layerListExpandedType": 2,
  "layers": [
    {
      "class": "group",
      "id": "1F0CFD8D-17C8-48C2-A1E5-2D3B8DA078E8"
    },
    {
      "class": "oval",
      "id": "6C6F65E7-7C5A-47C4-996F-FC70FB4D5CF4"
    }
  ],
  "name": "Notif",
  "nameIsFixed": true,
  "resizingConstraint": 63,
  "resizingType": 0,
  "rotation": 0,
  "shouldBreakMaskChain": false,
  "style": {
    "_class": "style",
    "do_objectID": "90E27548-A591-41F2-BFBD-A8AC092C417E",
    "endMarkerType": 0,
    "miterLimit": 10,
    "startMarkerType": 0,
    "windingRule": 1
  }
}