{
  "_class": "group",
  "booleanOperation": -1,
  "clippingMaskMode": 0,
  "do_objectID": "F9511697-69EA-49FF-9272-B1D9CFF0F091",
  "exportOptions": {
    "_class": "exportOptions",
    "do_objectID": "1480541D-3F7B-46BD-98E3-05FE11182F95",
    "exportFormats": [
    ],
    "includedLayerIds": [
    ],
    "layerOptions": 0,
    "shouldTrim": false
  },
  "frame": {
    "_class": "rect",
    "constrainProportions": false,
    "do_objectID": "D7F6326A-2F4D-43CA-B650-103F071DC7AD",
    "height": 49,
    "width": 48,
    "x": 13,
    "y": 16
  },
  "groupLayout": {
    "_class": "MSImmutableFreeformGroupLayout",
    "do_objectID": "F064B732-F0BC-41D7-89AF-C04B40B51F88"
  },
  "hasClickThrough": false,
  "hasClippingMask": false,
  "isFixedToViewport": false,
  "isFlippedHorizontal": false,
  "isFlippedVertical": false,
  "isLocked": false,
  "isVisible": true,
  "layerListExpandedType": 0,
  "layers": [
    {
      "class": "rectangle",
      "id": "F1C5F5B4-7087-4EB1-979C-E1113E3B8D76"
    },
    {
      "class": "bitmap",
      "id": "AD452059-D8F5-463C-8EDC-E2DBBEC24546"
    }
  ],
  "name": "Group 4",
  "nameIsFixed": false,
  "resizingConstraint": 63,
  "resizingType": 0,
  "rotation": 0,
  "shouldBreakMaskChain": false,
  "style": {
    "_class": "style",
    "do_objectID": "041E4A44-2977-4FF7-ABCD-2BE95BB52736",
    "endMarkerType": 0,
    "miterLimit": 10,
    "startMarkerType": 0,
    "windingRule": 1
  }
}