{
  "_class": "shapeGroup",
  "booleanOperation": -1,
  "clippingMaskMode": 0,
  "do_objectID": "3C2B5127-15FC-409F-A805-FA26A7BDB764",
  "exportOptions": {
    "_class": "exportOptions",
    "do_objectID": "7A4EF54B-5C62-489C-B350-AA712A7F0B11",
    "exportFormats": [
      {
        "_class": "exportFormat",
        "absoluteSize": 0,
        "fileFormat": "svg",
        "name": "",
        "namingScheme": 0,
        "scale": 1,
        "visibleScaleType": 0
      }
    ],
    "includedLayerIds": [
    ],
    "layerOptions": 0,
    "shouldTrim": false
  },
  "frame": {
    "_class": "rect",
    "constrainProportions": false,
    "do_objectID": "1171F4F3-F2B8-4FF3-9F4A-3844B70A6519",
    "height": 3.96875,
    "width": 3.96875,
    "x": 140.71875,
    "y": 401.65625
  },
  "groupLayout": {
    "_class": "MSImmutableFreeformGroupLayout",
    "do_objectID": "21BB706C-DA6D-400A-A2E4-2BA7698C93E7"
  },
  "hasClickThrough": false,
  "hasClippingMask": false,
  "isFixedToViewport": false,
  "isFlippedHorizontal": false,
  "isFlippedVertical": false,
  "isLocked": false,
  "isVisible": true,
  "layerListExpandedType": 2,
  "layers": [
    {
      "class": "shapePath",
      "id": "4BE75DDA-5102-4994-8CCD-B0242E8A2256"
    },
    {
      "class": "shapePath",
      "id": "8598E222-1912-4420-99ED-DD48820EED81"
    }
  ],
  "name": "Shape",
  "nameIsFixed": false,
  "resizingConstraint": 63,
  "resizingType": 0,
  "rotation": 0,
  "shouldBreakMaskChain": false,
  "style": {
    "_class": "style",
    "blur": {
      "_class": "blur",
      "center": "{0.5, 0.5}",
      "do_objectID": "2F106F74-3000-46FF-AC7F-D756410D4EC5",
      "isEnabled": false,
      "motionAngle": 0,
      "radius": 0.4266666666666666,
      "saturation": 1,
      "type": 0
    },
    "do_objectID": "643B2A1D-85B3-491E-B38D-B5C13428DB76",
    "endMarkerType": 0,
    "fills": [
      {
        "_class": "fill",
        "color": {
          "_class": "color",
          "alpha": 1,
          "blue": 0.3137254901960784,
          "green": 0.2941176470588235,
          "red": 0.2627450980392157
        },
        "fillType": 0,
        "isEnabled": true,
        "noiseIndex": 0,
        "noiseIntensity": 0,
        "patternFillType": 1,
        "patternTileScale": 1
      }
    ],
    "miterLimit": 10,
    "startMarkerType": 0,
    "windingRule": 0
  },
  "windingRule": 0
}