{
  "_class": "symbolInstance",
  "booleanOperation": 0,
  "clippingMaskMode": 0,
  "do_objectID": "815D7D8C-CA2F-4215-9785-A12B02231052",
  "exportOptions": {
    "_class": "exportOptions",
    "do_objectID": "B82297F3-A067-443F-B36E-1A1C6F5F3EA7",
    "exportFormats": [
    ],
    "includedLayerIds": [
    ],
    "layerOptions": 0,
    "shouldTrim": false
  },
  "frame": {
    "_class": "rect",
    "constrainProportions": false,
    "do_objectID": "35D9F9C7-BD4E-484C-A3E5-37019D355ECD",
    "height": 1,
    "width": 664,
    "x": 0,
    "y": 55
  },
  "hasClippingMask": false,
  "horizontalSpacing": 0,
  "isFixedToViewport": false,
  "isFlippedHorizontal": false,
  "isFlippedVertical": false,
  "isLocked": false,
  "isVisible": true,
  "layerListExpandedType": 0,
  "name": "UI/Color/Flat/Gray light",
  "nameIsFixed": false,
  "overrideValues": [
  ],
  "resizingConstraint": 63,
  "resizingType": 0,
  "rotation": 0,
  "scale": 1,
  "shouldBreakMaskChain": false,
  "style": {
    "_class": "style",
    "do_objectID": "EBCAC776-C998-433E-9C9F-8B55ECBD76CC",
    "endMarkerType": 0,
    "miterLimit": 10,
    "startMarkerType": 0,
    "windingRule": 1
  },
  "symbolID": "55C6BCF7-DBA7-44FC-901F-584136AC5DAA",
  "verticalSpacing": 0
}