{
  "_class": "symbolInstance",
  "booleanOperation": 0,
  "clippingMaskMode": 0,
  "do_objectID": "262B2A3A-6BAB-4673-AA80-687F526DCF25",
  "exportOptions": {
    "_class": "exportOptions",
    "do_objectID": "B1EF1D62-A949-47C3-A203-BEFEA846F241",
    "exportFormats": [
      {
        "_class": "exportFormat",
        "absoluteSize": 0,
        "fileFormat": "svg",
        "name": "",
        "namingScheme": 0,
        "scale": 1,
        "visibleScaleType": 0
      }
    ],
    "includedLayerIds": [
    ],
    "layerOptions": 0,
    "shouldTrim": false
  },
  "frame": {
    "_class": "rect",
    "constrainProportions": false,
    "do_objectID": "B8A69B90-F714-46E7-8F1E-F9F993267B52",
    "height": 44,
    "width": 375,
    "x": 0,
    "y": 0
  },
  "hasClippingMask": false,
  "horizontalSpacing": 0,
  "isFixedToViewport": false,
  "isFlippedHorizontal": false,
  "isFlippedVertical": false,
  "isLocked": false,
  "isVisible": true,
  "layerListExpandedType": 0,
  "name": "iPhone X/Status Bars/Status Bar (Black)",
  "nameIsFixed": false,
  "overrideValues": [
  ],
  "resizingConstraint": 10,
  "resizingType": 0,
  "rotation": 0,
  "scale": 1,
  "shouldBreakMaskChain": false,
  "style": {
    "_class": "style",
    "do_objectID": "18BB50DD-0251-42DB-B202-A7BC0CFF5567",
    "endMarkerType": 0,
    "miterLimit": 10,
    "startMarkerType": 0,
    "windingRule": 1
  },
  "symbolID": "7A8E7211-B304-4242-B70E-31BF722F39EE",
  "verticalSpacing": 0
}