{
  "_class": "group",
  "booleanOperation": 0,
  "clippingMaskMode": 0,
  "do_objectID": "A532180D-7D90-40D2-94AD-B8902443A769",
  "exportOptions": {
    "_class": "exportOptions",
    "do_objectID": "BB5F6356-A9D0-41E4-9115-DFB0F9568EF0",
    "exportFormats": [
    ],
    "includedLayerIds": [
    ],
    "layerOptions": 0,
    "shouldTrim": false
  },
  "frame": {
    "_class": "rect",
    "constrainProportions": false,
    "do_objectID": "6EF69BD0-E563-4E6F-987D-07A378A4E0DC",
    "height": 16,
    "width": 16,
    "x": 295,
    "y": 2
  },
  "groupLayout": {
    "_class": "MSImmutableFreeformGroupLayout",
    "do_objectID": "0C35023D-3B83-4E7D-9799-8B63AA671066"
  },
  "hasClickThrough": false,
  "hasClippingMask": false,
  "isFixedToViewport": false,
  "isFlippedHorizontal": false,
  "isFlippedVertical": false,
  "isLocked": false,
  "isVisible": true,
  "layerListExpandedType": 2,
  "layers": [
    {
      "class": "shapeGroup",
      "id": "ABFBAB9D-784A-49E8-ABFB-3B935CE4343D"
    }
  ],
  "name": "Arrow_left Copy",
  "nameIsFixed": false,
  "resizingConstraint": 63,
  "resizingType": 0,
  "rotation": 0,
  "shouldBreakMaskChain": false,
  "style": {
    "_class": "style",
    "blur": {
      "_class": "blur",
      "center": "{0.5, 0.5}",
      "do_objectID": "B080CDFF-C6EF-430F-B145-2E07FAAEDBAF",
      "isEnabled": false,
      "motionAngle": 0,
      "radius": 3.636363636363637,
      "saturation": 1,
      "type": 0
    },
    "do_objectID": "6C35898F-D894-4835-86D7-D7D0D082970C",
    "endMarkerType": 0,
    "fills": [
      {
        "_class": "fill",
        "color": {
          "_class": "color",
          "alpha": 1,
          "blue": 0,
          "green": 0,
          "red": 0
        },
        "fillType": 0,
        "isEnabled": true,
        "noiseIndex": 0,
        "noiseIntensity": 0,
        "patternFillType": 1,
        "patternTileScale": 1
      }
    ],
    "miterLimit": 10,
    "startMarkerType": 0,
    "windingRule": 1
  }
}